{
    "name": "Database\\Seeders\\ModeSeeder",
    "line": 10,
    "short_desc": null,
    "long_desc": null,
    "hint": null,
    "tags": [],
    "namespace": "Database\\Seeders",
    "file": "..\\database\\seeders\\ModeSeeder.php",
    "relative_file": null,
    "hash": "f0be3759133b8461b1b7dea47d0dbb02c4cdf914",
    "parent": "Illuminate\\Database\\Seeder",
    "modifiers": 0,
    "is_trait": false,
    "is_interface": false,
    "is_read_only": false,
    "aliases": {
        "WithoutModelEvents": "Illuminate\\Database\\Console\\Seeds\\WithoutModelEvents",
        "Seeder": "Illuminate\\Database\\Seeder",
        "Mode": "App\\Models\\Mode"
    },
    "errors": [],
    "interfaces": [],
    "traits": [],
    "properties": [],
    "methods": {
        "run": {
            "name": "run",
            "line": 16,
            "short_desc": "Run the database seeds.",
            "long_desc": "",
            "hint": [
                [
                    "void",
                    false
                ]
            ],
            "hint_desc": "",
            "tags": [],
            "see": [],
            "modifiers": 1,
            "is_by_ref": "",
            "exceptions": [],
            "errors": [],
            "parameters": []
        }
    },
    "constants": []
}